Workbook
Name AccountList: ChartOfAccounts!$A$2:$A$100

Sheet ChartOfAccounts
A1: Account | B1: Type | C1: Category
A2: Cash | B2: Asset | C2: Current Asset
A3: Equipment | B3: Asset | C3: Non-Current Asset
A4: Office Supplies | B4: Asset | C4: Current Asset
A5: Accounts Payable | B5: Liability | C5: Current Liability
A6: Owner's Capital | B6: Equity | C6: Owner Equity
A7: Rent Expense | B7: Expense | C7: Operating Expense
A8: Salaries Expense | B8: Expense | C8: Operating Expense
A9: Service Revenue | B9: Revenue | C9: Operating Revenue

Sheet NewTransaction
A1: Date | B1: Description | C1: Debit Account | D1: Credit Account | E1: Amount | F1: Balanced?
A2: 2026-09-01 | B2: Purchase equipment for cash | C2: Equipment | D2: Cash | E2: 18000 | F2: =IF(OR(A2="",C2="",D2="",E2=""),"",IF(OR(C2=D2,E2<=0),"✗","✓")) -> ✓
A3: 2026-09-02 | B3: Provide services and receive cash | C3: Cash | D3: Service Revenue | E3: 5600 | F3: =IF(OR(A3="",C3="",D3="",E3=""),"",IF(OR(C3=D3,E3<=0),"✗","✓")) -> ✓
A4: 2026-09-03 | B4: Pay current month's rent | C4: Rent Expense | D4: Cash | E4: 2700 | F4: =IF(OR(A4="",C4="",D4="",E4=""),"",IF(OR(C4=D4,E4<=0),"✗","✓")) -> ✓
A5: 2026-09-04 | B5: Purchase office supplies on account | C5: Office Supplies | D5: Accounts Payable | E5: 2200 | F5: =IF(OR(A5="",C5="",D5="",E5=""),"",IF(OR(C5=D5,E5<=0),"✗","✓")) -> ✓
A6: 2026-09-05 | B6: Pay employee salaries | C6: Salaries Expense | D6: Cash | E6: 3200 | F6: =IF(OR(A6="",C6="",D6="",E6=""),"",IF(OR(C6=D6,E6<=0),"✗","✓")) -> ✓
A7: 2026-09-01 | B7: Owner invests opening cash (balancing example) | C7: Cash | D7: Owner's Capital | E7: 18300 | F7: =IF(OR(A7="",C7="",D7="",E7=""),"",IF(OR(C7=D7,E7<=0),"✗","✓")) -> ✓
F8: =IF(OR(A8="",C8="",D8="",E8=""),"",IF(OR(C8=D8,E8<=0),"✗","✓"))
A9: NOTE | B9: The £18,300 Owner's Capital entry is included as a balancing example so the financial statements can be complete. Delete it if you want to practise the original five transactions only.
F11: =IF(OR(A11="",C11="",D11="",E11=""),"",IF(OR(C11=D11,E11<=0),"✗","✓"))
F12: =IF(OR(A12="",C12="",D12="",E12=""),"",IF(OR(C12=D12,E12<=0),"✗","✓"))
F13: =IF(OR(A13="",C13="",D13="",E13=""),"",IF(OR(C13=D13,E13<=0),"✗","✓"))
F14: =IF(OR(A14="",C14="",D14="",E14=""),"",IF(OR(C14=D14,E14<=0),"✗","✓"))
F15: =IF(OR(A15="",C15="",D15="",E15=""),"",IF(OR(C15=D15,E15<=0),"✗","✓"))
F16: =IF(OR(A16="",C16="",D16="",E16=""),"",IF(OR(C16=D16,E16<=0),"✗","✓"))
F17: =IF(OR(A17="",C17="",D17="",E17=""),"",IF(OR(C17=D17,E17<=0),"✗","✓"))
F18: =IF(OR(A18="",C18="",D18="",E18=""),"",IF(OR(C18=D18,E18<=0),"✗","✓"))
F19: =IF(OR(A19="",C19="",D19="",E19=""),"",IF(OR(C19=D19,E19<=0),"✗","✓"))
F20: =IF(OR(A20="",C20="",D20="",E20=""),"",IF(OR(C20=D20,E20<=0),"✗","✓"))
F21: =IF(OR(A21="",C21="",D21="",E21=""),"",IF(OR(C21=D21,E21<=0),"✗","✓"))
F22: =IF(OR(A22="",C22="",D22="",E22=""),"",IF(OR(C22=D22,E22<=0),"✗","✓"))
... F101: =IF(OR(A101="",C101="",D101="",E101=""),"",IF(OR(C101=D101,E101<=0),"✗","✓"))

Sheet Journal
A1: Date | B1: Description | C1: Account | D1: Debit | E1: Credit
A2: =IF(NewTransaction!A2="","",NewTransaction!A2) -> 2026-09-01 | B2: =IF(NewTransaction!A2="","",NewTransaction!B2) -> Purchase equipment for cash | C2: =IF(NewTransaction!A2="","",NewTransaction!C2) -> Equipment | D2: =IF(NewTransaction!A2="","",NewTransaction!E2) -> 18000 | E2: =IF(A2="","",0) -> 0
A3: =IF(NewTransaction!A2="","",NewTransaction!A2) -> 2026-09-01 | B3: =IF(NewTransaction!A2="","",NewTransaction!B2) -> Purchase equipment for cash | C3: =IF(NewTransaction!A2="","",NewTransaction!D2) -> Cash | D3: =IF(A3="","",0) -> 0 | E3: =IF(NewTransaction!A2="","",NewTransaction!E2) -> 18000
A4: =IF(NewTransaction!A3="","",NewTransaction!A3) -> 2026-09-02 | B4: =IF(NewTransaction!A3="","",NewTransaction!B3) -> Provide services and receive cash | C4: =IF(NewTransaction!A3="","",NewTransaction!C3) -> Cash | D4: =IF(NewTransaction!A3="","",NewTransaction!E3) -> 5600 | E4: =IF(A4="","",0) -> 0
A5: =IF(NewTransaction!A3="","",NewTransaction!A3) -> 2026-09-02 | B5: =IF(NewTransaction!A3="","",NewTransaction!B3) -> Provide services and receive cash | C5: =IF(NewTransaction!A3="","",NewTransaction!D3) -> Service Revenue | D5: =IF(A5="","",0) -> 0 | E5: =IF(NewTransaction!A3="","",NewTransaction!E3) -> 5600
A6: =IF(NewTransaction!A4="","",NewTransaction!A4) -> 2026-09-03 | B6: =IF(NewTransaction!A4="","",NewTransaction!B4) -> Pay current month's rent | C6: =IF(NewTransaction!A4="","",NewTransaction!C4) -> Rent Expense | D6: =IF(NewTransaction!A4="","",NewTransaction!E4) -> 2700 | E6: =IF(A6="","",0) -> 0
A7: =IF(NewTransaction!A4="","",NewTransaction!A4) -> 2026-09-03 | B7: =IF(NewTransaction!A4="","",NewTransaction!B4) -> Pay current month's rent | C7: =IF(NewTransaction!A4="","",NewTransaction!D4) -> Cash | D7: =IF(A7="","",0) -> 0 | E7: =IF(NewTransaction!A4="","",NewTransaction!E4) -> 2700
A8: =IF(NewTransaction!A5="","",NewTransaction!A5) -> 2026-09-04 | B8: =IF(NewTransaction!A5="","",NewTransaction!B5) -> Purchase office supplies on account | C8: =IF(NewTransaction!A5="","",NewTransaction!C5) -> Office Supplies | D8: =IF(NewTransaction!A5="","",NewTransaction!E5) -> 2200 | E8: =IF(A8="","",0) -> 0
A9: =IF(NewTransaction!A5="","",NewTransaction!A5) -> 2026-09-04 | B9: =IF(NewTransaction!A5="","",NewTransaction!B5) -> Purchase office supplies on account | C9: =IF(NewTransaction!A5="","",NewTransaction!D5) -> Accounts Payable | D9: =IF(A9="","",0) -> 0 | E9: =IF(NewTransaction!A5="","",NewTransaction!E5) -> 2200
A10: =IF(NewTransaction!A6="","",NewTransaction!A6) -> 2026-09-05 | B10: =IF(NewTransaction!A6="","",NewTransaction!B6) -> Pay employee salaries | C10: =IF(NewTransaction!A6="","",NewTransaction!C6) -> Salaries Expense | D10: =IF(NewTransaction!A6="","",NewTransaction!E6) -> 3200 | E10: =IF(A10="","",0) -> 0
A11: =IF(NewTransaction!A6="","",NewTransaction!A6) -> 2026-09-05 | B11: =IF(NewTransaction!A6="","",NewTransaction!B6) -> Pay employee salaries | C11: =IF(NewTransaction!A6="","",NewTransaction!D6) -> Cash | D11: =IF(A11="","",0) -> 0 | E11: =IF(NewTransaction!A6="","",NewTransaction!E6) -> 3200
A12: =IF(NewTransaction!A7="","",NewTransaction!A7) -> 2026-09-01 | B12: =IF(NewTransaction!A7="","",NewTransaction!B7) -> Owner invests opening cash (balancing example) | C12: =IF(NewTransaction!A7="","",NewTransaction!C7) -> Cash | D12: =IF(NewTransaction!A7="","",NewTransaction!E7) -> 18300 | E12: =IF(A12="","",0) -> 0
A13: =IF(NewTransaction!A7="","",NewTransaction!A7) -> 2026-09-01 | B13: =IF(NewTransaction!A7="","",NewTransaction!B7) -> Owner invests opening cash (balancing example) | C13: =IF(NewTransaction!A7="","",NewTransaction!D7) -> Owner's Capital | D13: =IF(A13="","",0) -> 0 | E13: =IF(NewTransaction!A7="","",NewTransaction!E7) -> 18300
A14: =IF(NewTransaction!A8="","",NewTransaction!A8) | B14: =IF(NewTransaction!A8="","",NewTransaction!B8) | C14: =IF(NewTransaction!A8="","",NewTransaction!C8) | D14: =IF(NewTransaction!A8="","",NewTransaction!E8) | E14: =IF(A14="","",0)
A15: =IF(NewTransaction!A8="","",NewTransaction!A8) | B15: =IF(NewTransaction!A8="","",NewTransaction!B8) | C15: =IF(NewTransaction!A8="","",NewTransaction!D8) | D15: =IF(A15="","",0) | E15: =IF(NewTransaction!A8="","",NewTransaction!E8)
A16: =IF(NewTransaction!A9="","",NewTransaction!A9) -> NOTE | B16: =IF(NewTransaction!A9="","",NewTransaction!B9) -> The £18,300 Owner's Capital entry is included as a balancing example so the financial statements can be complete. Delete it if you want to practise the original five transactions only. | C16: =IF(NewTransaction!A9="","",NewTransaction!C9) -> 0 | D16: =IF(NewTransaction!A9="","",NewTransaction!E9) -> 0 | E16: =IF(A16="","",0) -> 0
A17: =IF(NewTransaction!A9="","",NewTransaction!A9) -> NOTE | B17: =IF(NewTransaction!A9="","",NewTransaction!B9) -> The £18,300 Owner's Capital entry is included as a balancing example so the financial statements can be complete. Delete it if you want to practise the original five transactions only. | C17: =IF(NewTransaction!A9="","",NewTransaction!D9) -> 0 | D17: =IF(A17="","",0) -> 0 | E17: =IF(NewTransaction!A9="","",NewTransaction!E9) -> 0
A18: =IF(NewTransaction!A10="","",NewTransaction!A10) | B18: =IF(NewTransaction!A10="","",NewTransaction!B10) | C18: =IF(NewTransaction!A10="","",NewTransaction!C10) | D18: =IF(NewTransaction!A10="","",NewTransaction!E10) | E18: =IF(A18="","",0)
A19: =IF(NewTransaction!A10="","",NewTransaction!A10) | B19: =IF(NewTransaction!A10="","",NewTransaction!B10) | C19: =IF(NewTransaction!A10="","",NewTransaction!D10) | D19: =IF(A19="","",0) | E19: =IF(NewTransaction!A10="","",NewTransaction!E10)
A20: =IF(NewTransaction!A11="","",NewTransaction!A11) | B20: =IF(NewTransaction!A11="","",NewTransaction!B11) | C20: =IF(NewTransaction!A11="","",NewTransaction!C11) | D20: =IF(NewTransaction!A11="","",NewTransaction!E11) | E20: =IF(A20="","",0)
A21: =IF(NewTransaction!A11="","",NewTransaction!A11) | B21: =IF(NewTransaction!A11="","",NewTransaction!B11) | C21: =IF(NewTransaction!A11="","",NewTransaction!D11) | D21: =IF(A21="","",0) | E21: =IF(NewTransaction!A11="","",NewTransaction!E11)
A22: =IF(NewTransaction!A12="","",NewTransaction!A12) | B22: =IF(NewTransaction!A12="","",NewTransaction!B12) | C22: =IF(NewTransaction!A12="","",NewTransaction!C12) | D22: =IF(NewTransaction!A12="","",NewTransaction!E12) | E22: =IF(A22="","",0)
A23: =IF(NewTransaction!A12="","",NewTransaction!A12) | B23: =IF(NewTransaction!A12="","",NewTransaction!B12) | C23: =IF(NewTransaction!A12="","",NewTransaction!D12) | D23: =IF(A23="","",0) | E23: =IF(NewTransaction!A12="","",NewTransaction!E12)
A24: =IF(NewTransaction!A13="","",NewTransaction!A13) | B24: =IF(NewTransaction!A13="","",NewTransaction!B13) | C24: =IF(NewTransaction!A13="","",NewTransaction!C13) | D24: =IF(NewTransaction!A13="","",NewTransaction!E13) | E24: =IF(A24="","",0)
A25: =IF(NewTransaction!A13="","",NewTransaction!A13) | B25: =IF(NewTransaction!A13="","",NewTransaction!B13) | C25: =IF(NewTransaction!A13="","",NewTransaction!D13) | D25: =IF(A25="","",0) | E25: =IF(NewTransaction!A13="","",NewTransaction!E13)
A26: =IF(NewTransaction!A14="","",NewTransaction!A14) | B26: =IF(NewTransaction!A14="","",NewTransaction!B14) | C26: =IF(NewTransaction!A14="","",NewTransaction!C14) | D26: =IF(NewTransaction!A14="","",NewTransaction!E14) | E26: =IF(A26="","",0)
A27: =IF(NewTransaction!A14="","",NewTransaction!A14) | B27: =IF(NewTransaction!A14="","",NewTransaction!B14) | C27: =IF(NewTransaction!A14="","",NewTransaction!D14) | D27: =IF(A27="","",0) | E27: =IF(NewTransaction!A14="","",NewTransaction!E14)
A28: =IF(NewTransaction!A15="","",NewTransaction!A15) | B28: =IF(NewTransaction!A15="","",NewTransaction!B15) | C28: =IF(NewTransaction!A15="","",NewTransaction!C15) | D28: =IF(NewTransaction!A15="","",NewTransaction!E15) | E28: =IF(A28="","",0)
A29: =IF(NewTransaction!A15="","",NewTransaction!A15) | B29: =IF(NewTransaction!A15="","",NewTransaction!B15) | C29: =IF(NewTransaction!A15="","",NewTransaction!D15) | D29: =IF(A29="","",0) | E29: =IF(NewTransaction!A15="","",NewTransaction!E15)
A30: =IF(NewTransaction!A16="","",NewTransaction!A16) | B30: =IF(NewTransaction!A16="","",NewTransaction!B16) | C30: =IF(NewTransaction!A16="","",NewTransaction!C16) | D30: =IF(NewTransaction!A16="","",NewTransaction!E16) | E30: =IF(A30="","",0)
A31: =IF(NewTransaction!A16="","",NewTransaction!A16) | B31: =IF(NewTransaction!A16="","",NewTransaction!B16) | C31: =IF(NewTransaction!A16="","",NewTransaction!D16) | D31: =IF(A31="","",0) | E31: =IF(NewTransaction!A16="","",NewTransaction!E16)
A32: =IF(NewTransaction!A17="","",NewTransaction!A17) | B32: =IF(NewTransaction!A17="","",NewTransaction!B17) | C32: =IF(NewTransaction!A17="","",NewTransaction!C17) | D32: =IF(NewTransaction!A17="","",NewTransaction!E17) | E32: =IF(A32="","",0)
A33: =IF(NewTransaction!A17="","",NewTransaction!A17) | B33: =IF(NewTransaction!A17="","",NewTransaction!B17) | C33: =IF(NewTransaction!A17="","",NewTransaction!D17) | D33: =IF(A33="","",0) | E33: =IF(NewTransaction!A17="","",NewTransaction!E17)
A34: =IF(NewTransaction!A18="","",NewTransaction!A18) | B34: =IF(NewTransaction!A18="","",NewTransaction!B18) | C34: =IF(NewTransaction!A18="","",NewTransaction!C18) | D34: =IF(NewTransaction!A18="","",NewTransaction!E18) | E34: =IF(A34="","",0)
A35: =IF(NewTransaction!A18="","",NewTransaction!A18) | B35: =IF(NewTransaction!A18="","",NewTransaction!B18) | C35: =IF(NewTransaction!A18="","",NewTransaction!D18) | D35: =IF(A35="","",0) | E35: =IF(NewTransaction!A18="","",NewTransaction!E18)
A36: =IF(NewTransaction!A19="","",NewTransaction!A19) | B36: =IF(NewTransaction!A19="","",NewTransaction!B19) | C36: =IF(NewTransaction!A19="","",NewTransaction!C19) | D36: =IF(NewTransaction!A19="","",NewTransaction!E19) | E36: =IF(A36="","",0)
A37: =IF(NewTransaction!A19="","",NewTransaction!A19) | B37: =IF(NewTransaction!A19="","",NewTransaction!B19) | C37: =IF(NewTransaction!A19="","",NewTransaction!D19) | D37: =IF(A37="","",0) | E37: =IF(NewTransaction!A19="","",NewTransaction!E19)
A38: =IF(NewTransaction!A20="","",NewTransaction!A20) | B38: =IF(NewTransaction!A20="","",NewTransaction!B20) | C38: =IF(NewTransaction!A20="","",NewTransaction!C20) | D38: =IF(NewTransaction!A20="","",NewTransaction!E20) | E38: =IF(A38="","",0)
A39: =IF(NewTransaction!A20="","",NewTransaction!A20) | B39: =IF(NewTransaction!A20="","",NewTransaction!B20) | C39: =IF(NewTransaction!A20="","",NewTransaction!D20) | D39: =IF(A39="","",0) | E39: =IF(NewTransaction!A20="","",NewTransaction!E20)
A40: =IF(NewTransaction!A21="","",NewTransaction!A21) | B40: =IF(NewTransaction!A21="","",NewTransaction!B21) | C40: =IF(NewTransaction!A21="","",NewTransaction!C21) | D40: =IF(NewTransaction!A21="","",NewTransaction!E21) | E40: =IF(A40="","",0)
A41: =IF(NewTransaction!A21="","",NewTransaction!A21) | B41: =IF(NewTransaction!A21="","",NewTransaction!B21) | C41: =IF(NewTransaction!A21="","",NewTransaction!D21) | D41: =IF(A41="","",0) | E41: =IF(NewTransaction!A21="","",NewTransaction!E21)
A42: =IF(NewTransaction!A22="","",NewTransaction!A22) | B42: =IF(NewTransaction!A22="","",NewTransaction!B22) | C42: =IF(NewTransaction!A22="","",NewTransaction!C22) | D42: =IF(NewTransaction!A22="","",NewTransaction!E22) | E42: =IF(A42="","",0)
A43: =IF(NewTransaction!A22="","",NewTransaction!A22) | B43: =IF(NewTransaction!A22="","",NewTransaction!B22) | C43: =IF(NewTransaction!A22="","",NewTransaction!D22) | D43: =IF(A43="","",0) | E43: =IF(NewTransaction!A22="","",NewTransaction!E22)
A44: =IF(NewTransaction!A23="","",NewTransaction!A23) | B44: =IF(NewTransaction!A23="","",NewTransaction!B23) | C44: =IF(NewTransaction!A23="","",NewTransaction!C23) | D44: =IF(NewTransaction!A23="","",NewTransaction!E23) | E44: =IF(A44="","",0)
A45: =IF(NewTransaction!A23="","",NewTransaction!A23) | B45: =IF(NewTransaction!A23="","",NewTransaction!B23) | C45: =IF(NewTransaction!A23="","",NewTransaction!D23) | D45: =IF(A45="","",0) | E45: =IF(NewTransaction!A23="","",NewTransaction!E23)
A46: =IF(NewTransaction!A24="","",NewTransaction!A24) | B46: =IF(NewTransaction!A24="","",NewTransaction!B24) | C46: =IF(NewTransaction!A24="","",NewTransaction!C24) | D46: =IF(NewTransaction!A24="","",NewTransaction!E24) | E46: =IF(A46="","",0)
A47: =IF(NewTransaction!A24="","",NewTransaction!A24) | B47: =IF(NewTransaction!A24="","",NewTransaction!B24) | C47: =IF(NewTransaction!A24="","",NewTransaction!D24) | D47: =IF(A47="","",0) | E47: =IF(NewTransaction!A24="","",NewTransaction!E24)
A48: =IF(NewTransaction!A25="","",NewTransaction!A25) | B48: =IF(NewTransaction!A25="","",NewTransaction!B25) | C48: =IF(NewTransaction!A25="","",NewTransaction!C25) | D48: =IF(NewTransaction!A25="","",NewTransaction!E25) | E48: =IF(A48="","",0)
A49: =IF(NewTransaction!A25="","",NewTransaction!A25) | B49: =IF(NewTransaction!A25="","",NewTransaction!B25) | C49: =IF(NewTransaction!A25="","",NewTransaction!D25) | D49: =IF(A49="","",0) | E49: =IF(NewTransaction!A25="","",NewTransaction!E25)
A50: =IF(NewTransaction!A26="","",NewTransaction!A26) | B50: =IF(NewTransaction!A26="","",NewTransaction!B26) | C50: =IF(NewTransaction!A26="","",NewTransaction!C26) | D50: =IF(NewTransaction!A26="","",NewTransaction!E26) | E50: =IF(A50="","",0)
A51: =IF(NewTransaction!A26="","",NewTransaction!A26) | B51: =IF(NewTransaction!A26="","",NewTransaction!B26) | C51: =IF(NewTransaction!A26="","",NewTransaction!D26) | D51: =IF(A51="","",0) | E51: =IF(NewTransaction!A26="","",NewTransaction!E26)
A52: =IF(NewTransaction!A27="","",NewTransaction!A27) | B52: =IF(NewTransaction!A27="","",NewTransaction!B27) | C52: =IF(NewTransaction!A27="","",NewTransaction!C27) | D52: =IF(NewTransaction!A27="","",NewTransaction!E27) | E52: =IF(A52="","",0)
A53: =IF(NewTransaction!A27="","",NewTransaction!A27) | B53: =IF(NewTransaction!A27="","",NewTransaction!B27) | C53: =IF(NewTransaction!A27="","",NewTransaction!D27) | D53: =IF(A53="","",0) | E53: =IF(NewTransaction!A27="","",NewTransaction!E27)
A54: =IF(NewTransaction!A28="","",NewTransaction!A28) | B54: =IF(NewTransaction!A28="","",NewTransaction!B28) | C54: =IF(NewTransaction!A28="","",NewTransaction!C28) | D54: =IF(NewTransaction!A28="","",NewTransaction!E28) | E54: =IF(A54="","",0)
A55: =IF(NewTransaction!A28="","",NewTransaction!A28) | B55: =IF(NewTransaction!A28="","",NewTransaction!B28) | C55: =IF(NewTransaction!A28="","",NewTransaction!D28) | D55: =IF(A55="","",0) | E55: =IF(NewTransaction!A28="","",NewTransaction!E28)
A56: =IF(NewTransaction!A29="","",NewTransaction!A29) | B56: =IF(NewTransaction!A29="","",NewTransaction!B29) | C56: =IF(NewTransaction!A29="","",NewTransaction!C29) | D56: =IF(NewTransaction!A29="","",NewTransaction!E29) | E56: =IF(A56="","",0)
A57: =IF(NewTransaction!A29="","",NewTransaction!A29) | B57: =IF(NewTransaction!A29="","",NewTransaction!B29) | C57: =IF(NewTransaction!A29="","",NewTransaction!D29) | D57: =IF(A57="","",0) | E57: =IF(NewTransaction!A29="","",NewTransaction!E29)
A58: =IF(NewTransaction!A30="","",NewTransaction!A30) | B58: =IF(NewTransaction!A30="","",NewTransaction!B30) | C58: =IF(NewTransaction!A30="","",NewTransaction!C30) | D58: =IF(NewTransaction!A30="","",NewTransaction!E30) | E58: =IF(A58="","",0)
A59: =IF(NewTransaction!A30="","",NewTransaction!A30) | B59: =IF(NewTransaction!A30="","",NewTransaction!B30) | C59: =IF(NewTransaction!A30="","",NewTransaction!D30) | D59: =IF(A59="","",0) | E59: =IF(NewTransaction!A30="","",NewTransaction!E30)
A60: =IF(NewTransaction!A31="","",NewTransaction!A31) | B60: =IF(NewTransaction!A31="","",NewTransaction!B31) | C60: =IF(NewTransaction!A31="","",NewTransaction!C31) | D60: =IF(NewTransaction!A31="","",NewTransaction!E31) | E60: =IF(A60="","",0)
A61: =IF(NewTransaction!A31="","",NewTransaction!A31) | B61: =IF(NewTransaction!A31="","",NewTransaction!B31) | C61: =IF(NewTransaction!A31="","",NewTransaction!D31) | D61: =IF(A61="","",0) | E61: =IF(NewTransaction!A31="","",NewTransaction!E31)
A62: =IF(NewTransaction!A32="","",NewTransaction!A32) | B62: =IF(NewTransaction!A32="","",NewTransaction!B32) | C62: =IF(NewTransaction!A32="","",NewTransaction!C32) | D62: =IF(NewTransaction!A32="","",NewTransaction!E32) | E62: =IF(A62="","",0)
A63: =IF(NewTransaction!A32="","",NewTransaction!A32) | B63: =IF(NewTransaction!A32="","",NewTransaction!B32) | C63: =IF(NewTransaction!A32="","",NewTransaction!D32) | D63: =IF(A63="","",0) | E63: =IF(NewTransaction!A32="","",NewTransaction!E32)
A64: =IF(NewTransaction!A33="","",NewTransaction!A33) | B64: =IF(NewTransaction!A33="","",NewTransaction!B33) | C64: =IF(NewTransaction!A33="","",NewTransaction!C33) | D64: =IF(NewTransaction!A33="","",NewTransaction!E33) | E64: =IF(A64="","",0)
A65: =IF(NewTransaction!A33="","",NewTransaction!A33) | B65: =IF(NewTransaction!A33="","",NewTransaction!B33) | C65: =IF(NewTransaction!A33="","",NewTransaction!D33) | D65: =IF(A65="","",0) | E65: =IF(NewTransaction!A33="","",NewTransaction!E33)
A66: =IF(NewTransaction!A34="","",NewTransaction!A34) | B66: =IF(NewTransaction!A34="","",NewTransaction!B34) | C66: =IF(NewTransaction!A34="","",NewTransaction!C34) | D66: =IF(NewTransaction!A34="","",NewTransaction!E34) | E66: =IF(A66="","",0)
A67: =IF(NewTransaction!A34="","",NewTransaction!A34) | B67: =IF(NewTransaction!A34="","",NewTransaction!B34) | C67: =IF(NewTransaction!A34="","",NewTransaction!D34) | D67: =IF(A67="","",0) | E67: =IF(NewTransaction!A34="","",NewTransaction!E34)
A68: =IF(NewTransaction!A35="","",NewTransaction!A35) | B68: =IF(NewTransaction!A35="","",NewTransaction!B35) | C68: =IF(NewTransaction!A35="","",NewTransaction!C35) | D68: =IF(NewTransaction!A35="","",NewTransaction!E35) | E68: =IF(A68="","",0)
A69: =IF(NewTransaction!A35="","",NewTransaction!A35) | B69: =IF(NewTransaction!A35="","",NewTransaction!B35) | C69: =IF(NewTransaction!A35="","",NewTransaction!D35) | D69: =IF(A69="","",0) | E69: =IF(NewTransaction!A35="","",NewTransaction!E35)
A70: =IF(NewTransaction!A36="","",NewTransaction!A36) | B70: =IF(NewTransaction!A36="","",NewTransaction!B36) | C70: =IF(NewTransaction!A36="","",NewTransaction!C36) | D70: =IF(NewTransaction!A36="","",NewTransaction!E36) | E70: =IF(A70="","",0)
A71: =IF(NewTransaction!A36="","",NewTransaction!A36) | B71: =IF(NewTransaction!A36="","",NewTransaction!B36) | C71: =IF(NewTransaction!A36="","",NewTransaction!D36) | D71: =IF(A71="","",0) | E71: =IF(NewTransaction!A36="","",NewTransaction!E36)
A72: =IF(NewTransaction!A37="","",NewTransaction!A37) | B72: =IF(NewTransaction!A37="","",NewTransaction!B37) | C72: =IF(NewTransaction!A37="","",NewTransaction!C37) | D72: =IF(NewTransaction!A37="","",NewTransaction!E37) | E72: =IF(A72="","",0)
A73: =IF(NewTransaction!A37="","",NewTransaction!A37) | B73: =IF(NewTransaction!A37="","",NewTransaction!B37) | C73: =IF(NewTransaction!A37="","",NewTransaction!D37) | D73: =IF(A73="","",0) | E73: =IF(NewTransaction!A37="","",NewTransaction!E37)
A74: =IF(NewTransaction!A38="","",NewTransaction!A38) | B74: =IF(NewTransaction!A38="","",NewTransaction!B38) | C74: =IF(NewTransaction!A38="","",NewTransaction!C38) | D74: =IF(NewTransaction!A38="","",NewTransaction!E38) | E74: =IF(A74="","",0)
A75: =IF(NewTransaction!A38="","",NewTransaction!A38) | B75: =IF(NewTransaction!A38="","",NewTransaction!B38) | C75: =IF(NewTransaction!A38="","",NewTransaction!D38) | D75: =IF(A75="","",0) | E75: =IF(NewTransaction!A38="","",NewTransaction!E38)
A76: =IF(NewTransaction!A39="","",NewTransaction!A39) | B76: =IF(NewTransaction!A39="","",NewTransaction!B39) | C76: =IF(NewTransaction!A39="","",NewTransaction!C39) | D76: =IF(NewTransaction!A39="","",NewTransaction!E39) | E76: =IF(A76="","",0)
A77: =IF(NewTransaction!A39="","",NewTransaction!A39) | B77: =IF(NewTransaction!A39="","",NewTransaction!B39) | C77: =IF(NewTransaction!A39="","",NewTransaction!D39) | D77: =IF(A77="","",0) | E77: =IF(NewTransaction!A39="","",NewTransaction!E39)
A78: =IF(NewTransaction!A40="","",NewTransaction!A40) | B78: =IF(NewTransaction!A40="","",NewTransaction!B40) | C78: =IF(NewTransaction!A40="","",NewTransaction!C40) | D78: =IF(NewTransaction!A40="","",NewTransaction!E40) | E78: =IF(A78="","",0)
A79: =IF(NewTransaction!A40="","",NewTransaction!A40) | B79: =IF(NewTransaction!A40="","",NewTransaction!B40) | C79: =IF(NewTransaction!A40="","",NewTransaction!D40) | D79: =IF(A79="","",0) | E79: =IF(NewTransaction!A40="","",NewTransaction!E40)
A80: =IF(NewTransaction!A41="","",NewTransaction!A41) | B80: =IF(NewTransaction!A41="","",NewTransaction!B41) | C80: =IF(NewTransaction!A41="","",NewTransaction!C41) | D80: =IF(NewTransaction!A41="","",NewTransaction!E41) | E80: =IF(A80="","",0)
A81: =IF(NewTransaction!A41="","",NewTransaction!A41) | B81: =IF(NewTransaction!A41="","",NewTransaction!B41) | C81: =IF(NewTransaction!A41="","",NewTransaction!D41) | D81: =IF(A81="","",0) | E81: =IF(NewTransaction!A41="","",NewTransaction!E41)
A82: =IF(NewTransaction!A42="","",NewTransaction!A42) | B82: =IF(NewTransaction!A42="","",NewTransaction!B42) | C82: =IF(NewTransaction!A42="","",NewTransaction!C42) | D82: =IF(NewTransaction!A42="","",NewTransaction!E42) | E82: =IF(A82="","",0)
A83: =IF(NewTransaction!A42="","",NewTransaction!A42) | B83: =IF(NewTransaction!A42="","",NewTransaction!B42) | C83: =IF(NewTransaction!A42="","",NewTransaction!D42) | D83: =IF(A83="","",0) | E83: =IF(NewTransaction!A42="","",NewTransaction!E42)
A84: =IF(NewTransaction!A43="","",NewTransaction!A43) | B84: =IF(NewTransaction!A43="","",NewTransaction!B43) | C84: =IF(NewTransaction!A43="","",NewTransaction!C43) | D84: =IF(NewTransaction!A43="","",NewTransaction!E43) | E84: =IF(A84="","",0)
A85: =IF(NewTransaction!A43="","",NewTransaction!A43) | B85: =IF(NewTransaction!A43="","",NewTransaction!B43) | C85: =IF(NewTransaction!A43="","",NewTransaction!D43) | D85: =IF(A85="","",0) | E85: =IF(NewTransaction!A43="","",NewTransaction!E43)
A86: =IF(NewTransaction!A44="","",NewTransaction!A44) | B86: =IF(NewTransaction!A44="","",NewTransaction!B44) | C86: =IF(NewTransaction!A44="","",NewTransaction!C44) | D86: =IF(NewTransaction!A44="","",NewTransaction!E44) | E86: =IF(A86="","",0)
A87: =IF(NewTransaction!A44="","",NewTransaction!A44) | B87: =IF(NewTransaction!A44="","",NewTransaction!B44) | C87: =IF(NewTransaction!A44="","",NewTransaction!D44) | D87: =IF(A87="","",0) | E87: =IF(NewTransaction!A44="","",NewTransaction!E44)
A88: =IF(NewTransaction!A45="","",NewTransaction!A45) | B88: =IF(NewTransaction!A45="","",NewTransaction!B45) | C88: =IF(NewTransaction!A45="","",NewTransaction!C45) | D88: =IF(NewTransaction!A45="","",NewTransaction!E45) | E88: =IF(A88="","",0)
A89: =IF(NewTransaction!A45="","",NewTransaction!A45) | B89: =IF(NewTransaction!A45="","",NewTransaction!B45) | C89: =IF(NewTransaction!A45="","",NewTransaction!D45) | D89: =IF(A89="","",0) | E89: =IF(NewTransaction!A45="","",NewTransaction!E45)
A90: =IF(NewTransaction!A46="","",NewTransaction!A46) | B90: =IF(NewTransaction!A46="","",NewTransaction!B46) | C90: =IF(NewTransaction!A46="","",NewTransaction!C46) | D90: =IF(NewTransaction!A46="","",NewTransaction!E46) | E90: =IF(A90="","",0)
A91: =IF(NewTransaction!A46="","",NewTransaction!A46) | B91: =IF(NewTransaction!A46="","",NewTransaction!B46) | C91: =IF(NewTransaction!A46="","",NewTransaction!D46) | D91: =IF(A91="","",0) | E91: =IF(NewTransaction!A46="","",NewTransaction!E46)
A92: =IF(NewTransaction!A47="","",NewTransaction!A47) | B92: =IF(NewTransaction!A47="","",NewTransaction!B47) | C92: =IF(NewTransaction!A47="","",NewTransaction!C47) | D92: =IF(NewTransaction!A47="","",NewTransaction!E47) | E92: =IF(A92="","",0)
A93: =IF(NewTransaction!A47="","",NewTransaction!A47) | B93: =IF(NewTransaction!A47="","",NewTransaction!B47) | C93: =IF(NewTransaction!A47="","",NewTransaction!D47) | D93: =IF(A93="","",0) | E93: =IF(NewTransaction!A47="","",NewTransaction!E47)
A94: =IF(NewTransaction!A48="","",NewTransaction!A48) | B94: =IF(NewTransaction!A48="","",NewTransaction!B48) | C94: =IF(NewTransaction!A48="","",NewTransaction!C48) | D94: =IF(NewTransaction!A48="","",NewTransaction!E48) | E94: =IF(A94="","",0)
A95: =IF(NewTransaction!A48="","",NewTransaction!A48) | B95: =IF(NewTransaction!A48="","",NewTransaction!B48) | C95: =IF(NewTransaction!A48="","",NewTransaction!D48) | D95: =IF(A95="","",0) | E95: =IF(NewTransaction!A48="","",NewTransaction!E48)
A96: =IF(NewTransaction!A49="","",NewTransaction!A49) | B96: =IF(NewTransaction!A49="","",NewTransaction!B49) | C96: =IF(NewTransaction!A49="","",NewTransaction!C49) | D96: =IF(NewTransaction!A49="","",NewTransaction!E49) | E96: =IF(A96="","",0)
A97: =IF(NewTransaction!A49="","",NewTransaction!A49) | B97: =IF(NewTransaction!A49="","",NewTransaction!B49) | C97: =IF(NewTransaction!A49="","",NewTransaction!D49) | D97: =IF(A97="","",0) | E97: =IF(NewTransaction!A49="","",NewTransaction!E49)
A98: =IF(NewTransaction!A50="","",NewTransaction!A50) | B98: =IF(NewTransaction!A50="","",NewTransaction!B50) | C98: =IF(NewTransaction!A50="","",NewTransaction!C50) | D98: =IF(NewTransaction!A50="","",NewTransaction!E50) | E98: =IF(A98="","",0)
A99: =IF(NewTransaction!A50="","",NewTransaction!A50) | B99: =IF(NewTransaction!A50="","",NewTransaction!B50) | C99: =IF(NewTransaction!A50="","",NewTransaction!D50) | D99: =IF(A99="","",0) | E99: =IF(NewTransaction!A50="","",NewTransaction!E50)
A100: =IF(NewTransaction!A51="","",NewTransaction!A51) | B100: =IF(NewTransaction!A51="","",NewTransaction!B51) | C100: =IF(NewTransaction!A51="","",NewTransaction!C51) | D100: =IF(NewTransaction!A51="","",NewTransaction!E51) | E100: =IF(A100="","",0)
...

Sheet Ledger
A1: Account | B1: Total Debit | C1: Total Credit | D1: Balance | E1: Normal Balance | F1: Status
A2: =ChartOfAccounts!A2 -> Cash | B2: =SUMIF(Journal!$C:$C,A2,Journal!$D:$D) -> 23900 | C2: =SUMIF(Journal!$C:$C,A2,Journal!$E:$E) -> 23900 | D2: =B2-C2 -> 0 | E2: =IF(OR(A2="Cash",A2="Equipment",A2="Office Supplies",A2="Rent Expense",A2="Salaries Expense"),"Debit","Credit") -> Debit | F2: =IF(OR(AND(E2="Debit",D2>=0),AND(E2="Credit",D2<=0)),"OK","Check") -> OK
A3: =ChartOfAccounts!A3 -> Equipment | B3: =SUMIF(Journal!$C:$C,A3,Journal!$D:$D) -> 18000 | C3: =SUMIF(Journal!$C:$C,A3,Journal!$E:$E) -> 0 | D3: =B3-C3 -> 18000 | E3: =IF(OR(A3="Cash",A3="Equipment",A3="Office Supplies",A3="Rent Expense",A3="Salaries Expense"),"Debit","Credit") -> Debit | F3: =IF(OR(AND(E3="Debit",D3>=0),AND(E3="Credit",D3<=0)),"OK","Check") -> OK
A4: =ChartOfAccounts!A4 -> Office Supplies | B4: =SUMIF(Journal!$C:$C,A4,Journal!$D:$D) -> 2200 | C4: =SUMIF(Journal!$C:$C,A4,Journal!$E:$E) -> 0 | D4: =B4-C4 -> 2200 | E4: =IF(OR(A4="Cash",A4="Equipment",A4="Office Supplies",A4="Rent Expense",A4="Salaries Expense"),"Debit","Credit") -> Debit | F4: =IF(OR(AND(E4="Debit",D4>=0),AND(E4="Credit",D4<=0)),"OK","Check") -> OK
A5: =ChartOfAccounts!A5 -> Accounts Payable | B5: =SUMIF(Journal!$C:$C,A5,Journal!$D:$D) -> 0 | C5: =SUMIF(Journal!$C:$C,A5,Journal!$E:$E) -> 2200 | D5: =B5-C5 -> -2200 | E5: =IF(OR(A5="Cash",A5="Equipment",A5="Office Supplies",A5="Rent Expense",A5="Salaries Expense"),"Debit","Credit") -> Credit | F5: =IF(OR(AND(E5="Debit",D5>=0),AND(E5="Credit",D5<=0)),"OK","Check") -> OK
A6: =ChartOfAccounts!A6 -> Owner's Capital | B6: =SUMIF(Journal!$C:$C,A6,Journal!$D:$D) -> 0 | C6: =SUMIF(Journal!$C:$C,A6,Journal!$E:$E) -> 18300 | D6: =B6-C6 -> -18300 | E6: =IF(OR(A6="Cash",A6="Equipment",A6="Office Supplies",A6="Rent Expense",A6="Salaries Expense"),"Debit","Credit") -> Credit | F6: =IF(OR(AND(E6="Debit",D6>=0),AND(E6="Credit",D6<=0)),"OK","Check") -> OK
A7: =ChartOfAccounts!A7 -> Rent Expense | B7: =SUMIF(Journal!$C:$C,A7,Journal!$D:$D) -> 2700 | C7: =SUMIF(Journal!$C:$C,A7,Journal!$E:$E) -> 0 | D7: =B7-C7 -> 2700 | E7: =IF(OR(A7="Cash",A7="Equipment",A7="Office Supplies",A7="Rent Expense",A7="Salaries Expense"),"Debit","Credit") -> Debit | F7: =IF(OR(AND(E7="Debit",D7>=0),AND(E7="Credit",D7<=0)),"OK","Check") -> OK
A8: =ChartOfAccounts!A8 -> Salaries Expense | B8: =SUMIF(Journal!$C:$C,A8,Journal!$D:$D) -> 3200 | C8: =SUMIF(Journal!$C:$C,A8,Journal!$E:$E) -> 0 | D8: =B8-C8 -> 3200 | E8: =IF(OR(A8="Cash",A8="Equipment",A8="Office Supplies",A8="Rent Expense",A8="Salaries Expense"),"Debit","Credit") -> Debit | F8: =IF(OR(AND(E8="Debit",D8>=0),AND(E8="Credit",D8<=0)),"OK","Check") -> OK

Sheet TAccounts
A1: T-ACCOUNTS
A3: Cash | B3: Debit | C3: Credit
A4: Total | B4: =SUMIF(Journal!$C:$C,A3,Journal!$D:$D) -> 23900 | C4: =SUMIF(Journal!$C:$C,A3,Journal!$E:$E) -> 23900
A5: Balance | B5: =B4-C4 -> 0
A8: Equipment | B8: Debit | C8: Credit
A9: Total | B9: =SUMIF(Journal!$C:$C,A8,Journal!$D:$D) -> 18000 | C9: =SUMIF(Journal!$C:$C,A8,Journal!$E:$E) -> 0
A10: Balance | B10: =B9-C9 -> 18000
A13: Office Supplies | B13: Debit | C13: Credit
A14: Total | B14: =SUMIF(Journal!$C:$C,A13,Journal!$D:$D) -> 2200 | C14: =SUMIF(Journal!$C:$C,A13,Journal!$E:$E) -> 0
A15: Balance | B15: =B14-C14 -> 2200
A18: Accounts Payable | B18: Debit | C18: Credit
A19: Total | B19: =SUMIF(Journal!$C:$C,A18,Journal!$D:$D) -> 0 | C19: =SUMIF(Journal!$C:$C,A18,Journal!$E:$E) -> 2200
A20: Balance | B20: =B19-C19 -> -2200
A23: Owner's Capital | B23: Debit | C23: Credit
A24: Total | B24: =SUMIF(Journal!$C:$C,A23,Journal!$D:$D) -> 0 | C24: =SUMIF(Journal!$C:$C,A23,Journal!$E:$E) -> 18300
A25: Balance | B25: =B24-C24 -> -18300
A28: Rent Expense | B28: Debit | C28: Credit
A29: Total | B29: =SUMIF(Journal!$C:$C,A28,Journal!$D:$D) -> 2700 | C29: =SUMIF(Journal!$C:$C,A28,Journal!$E:$E) -> 0
A30: Balance | B30: =B29-C29 -> 2700
A33: Salaries Expense | B33: Debit | C33: Credit
A34: Total | B34: =SUMIF(Journal!$C:$C,A33,Journal!$D:$D) -> 3200 | C34: =SUMIF(Journal!$C:$C,A33,Journal!$E:$E) -> 0
A35: Balance | B35: =B34-C34 -> 3200
A38: Service Revenue | B38: Debit | C38: Credit
A39: Total | B39: =SUMIF(Journal!$C:$C,A38,Journal!$D:$D) -> 0 | C39: =SUMIF(Journal!$C:$C,A38,Journal!$E:$E) -> 5600
A40: Balance | B40: =B39-C39 -> -5600

Sheet TrialBalance
A1: Account | B1: Debit | C1: Credit
A2: =ChartOfAccounts!A2 -> Cash | B2: =IF(Ledger!D2>0,Ledger!D2,"") | C2: =IF(Ledger!D2<0,-Ledger!D2,"")
A3: =ChartOfAccounts!A3 -> Equipment | B3: =IF(Ledger!D3>0,Ledger!D3,"") -> 18000 | C3: =IF(Ledger!D3<0,-Ledger!D3,"")
A4: =ChartOfAccounts!A4 -> Office Supplies | B4: =IF(Ledger!D4>0,Ledger!D4,"") -> 2200 | C4: =IF(Ledger!D4<0,-Ledger!D4,"")
A5: =ChartOfAccounts!A5 -> Accounts Payable | B5: =IF(Ledger!D5>0,Ledger!D5,"") | C5: =IF(Ledger!D5<0,-Ledger!D5,"") -> 2200
A6: =ChartOfAccounts!A6 -> Owner's Capital | B6: =IF(Ledger!D6>0,Ledger!D6,"") | C6: =IF(Ledger!D6<0,-Ledger!D6,"") -> 18300
A7: =ChartOfAccounts!A7 -> Rent Expense | B7: =IF(Ledger!D7>0,Ledger!D7,"") -> 2700 | C7: =IF(Ledger!D7<0,-Ledger!D7,"")
A8: =ChartOfAccounts!A8 -> Salaries Expense | B8: =IF(Ledger!D8>0,Ledger!D8,"") -> 3200 | C8: =IF(Ledger!D8<0,-Ledger!D8,"")
A10: TOTAL | B10: =SUM(B2:B8) -> 26100 | C10: =SUM(C2:C8) -> 20500
A11: Difference | B11: =B10-C10 -> 5600
A12: Status | B12: =IF(ABS(B11)<0.01,"BALANCED","ERROR") -> ERROR

Sheet FinancialStatements
A1: FINANCIAL STATEMENTS
A3: INCOME STATEMENT | D3: BALANCE SHEET
A4: Service Revenue | B4: =SUMIF(TrialBalance!A:A,"*Revenue*",TrialBalance!C:C) -> 0 | D4: Assets
A5: Rent Expense | B5: =-SUMIF(TrialBalance!A:A,"*Rent Expense*",TrialBalance!B:B) -> -2700 | D5: Cash | E5: =IFERROR(INDEX(TrialBalance!B:B,MATCH("Cash",TrialBalance!A:A,0))-INDEX(TrialBalance!C:C,MATCH("Cash",TrialBalance!A:A,0)),0) -> 0
A6: Salaries Expense | B6: =-SUMIF(TrialBalance!A:A,"*Salaries Expense*",TrialBalance!B:B) -> -3200 | D6: Equipment | E6: =IFERROR(INDEX(TrialBalance!B:B,MATCH("Equipment",TrialBalance!A:A,0))-INDEX(TrialBalance!C:C,MATCH("Equipment",TrialBalance!A:A,0)),0) -> 0
A7: Total Expenses | B7: =SUM(B5:B6) -> -5900 | D7: Office Supplies | E7: =IFERROR(INDEX(TrialBalance!B:B,MATCH("Office Supplies",TrialBalance!A:A,0))-INDEX(TrialBalance!C:C,MATCH("Office Supplies",TrialBalance!A:A,0)),0) -> 0
A8: NET PROFIT / (LOSS) | B8: =B4+B7 -> -5900 | D8: Total Assets | E8: =SUM(E5:E7) -> 0
D10: Liabilities
D11: Accounts Payable | E11: =IFERROR(INDEX(TrialBalance!C:C,MATCH("Accounts Payable",TrialBalance!A:A,0))-INDEX(TrialBalance!B:B,MATCH("Accounts Payable",TrialBalance!A:A,0)),0) -> 0
D12: Total Liabilities | E12: =E11 -> 0
D14: Equity
D15: Owner's Capital | E15: =IFERROR(INDEX(TrialBalance!C:C,MATCH("Owner's Capital",TrialBalance!A:A,0))-INDEX(TrialBalance!B:B,MATCH("Owner's Capital",TrialBalance!A:A,0)),0) -> 0
D16: Current Profit / (Loss) | E16: =B8 -> -5900
D17: Total Equity | E17: =SUM(E15:E16) -> -5900
D19: Liabilities + Equity | E19: =E12+E17 -> -5900
D20: Balance Check | E20: =E8-E19 -> 5900
D21: Status | E21: =IF(ABS(E20)<0.01,"BALANCED","CHECK") -> CHECK
